workingdays/__init__.py
workingdays/_version.py
workingdays/date_utilities.py
workingdays/tests/__init__.py
workingdays/tests/_test_setup.py
workingdays/tests/test_workingdays.py
workingdays/tests/__pycache__/__init__.cpython-37.pyc
workingdays/tests/__pycache__/_test_setup.cpython-37.pyc
workingdays/tests/__pycache__/testSetup.cpython-37.pyc
workingdays-20.10.3.dist-info/COPYING
workingdays-20.10.3.dist-info/METADATA
workingdays-20.10.3.dist-info/WHEEL
workingdays-20.10.3.dist-info/top_level.txt
workingdays-20.10.3.dist-info/RECORD
