Metadata-Version: 2.1
Name: workingdays
Version: 20.10.3
Summary: A collection of Workingdays date utilities/helper functions.
Home-page: https://github.com/jeramiefletcher/workingdays
Author: Jeramie Fletcher
Author-email: jeramie.fletcher@gmail.com
License: GNU General Public License v3.0
Platform: UNKNOWN
Requires-Dist: workingdays
